filestore_guagua/__init__.py
filestore_guagua/filestore.py
filestore_guagua-0.1.1.dist-info/LICENSE
filestore_guagua-0.1.1.dist-info/METADATA
filestore_guagua-0.1.1.dist-info/WHEEL
filestore_guagua-0.1.1.dist-info/entry_points.txt
filestore_guagua-0.1.1.dist-info/top_level.txt
filestore_guagua-0.1.1.dist-info/RECORD
