Metadata-Version: 2.2
Name: filestore_guagua
Version: 0.1.1
Summary: guagua自用文件存储库
Author-email: guagua <guagua1053@gmail.com>
Maintainer-email: "jex.huang" <guagua1053@gmail.com>
License: MIT License
Project-URL: Homepage, https://github.com/dream-until-dawn/filestore_guagua
Project-URL: Bug Reports, https://github.com/dream-until-dawn/filestore_guagua/issues
Keywords: jex,files,python
Classifier: Programming Language :: Python :: 3
Classifier: Operating System :: OS Independent
Requires-Python: >=3.9
License-File: LICENSE
Provides-Extra: dev
Requires-Dist: check-manifest; extra == "dev"
Provides-Extra: test
Requires-Dist: coverage; extra == "test"
